<?xml version='1.0'?>
<ns2:test-suite xmlns:ns2='urn:model.allure.qatools.yandex.ru' start='1703355971463' stop='1703356013702'>
    <name>SnapTrude:</name>
    <title>SnapTrude:</title>
    <test-cases>
        <test-case start='1703355971973' status='passed' stop='1703355997511'>
            <name>Login</name>
            <title>Login</title>
            <labels>
                <label name='language' value='javascript'/>
                <label name='framework' value='codeceptjs'/>
            </labels>
            <parameters/>
            <steps>
                <step start='1703355971994' status='passed' stop='1703355982228'>
                    <name>I: login </name>
                    <title>I: login </title>
                    <attachments/>
                    <steps>
                        <step start='1703355971994' status='passed' stop='1703355980994'>
                            <name>I am on page "/login"</name>
                            <title>I am on page "/login"</title>
                            <attachments/>
                            <steps/>
                        </step>
                        <step start='1703355980995' status='passed' stop='1703355981643'>
                            <name>I fill field "div#root div:nth-child(1) > input", "chetan.g.shavanti@gmail.com"</name>
                            <title>I fill field "div#root div:nth-child(1) > input", "chetan.g.shavanti@gmail.com"</title>
                            <attachments/>
                            <steps/>
                        </step>
                        <step start='1703355981643' status='passed' stop='1703355982004'>
                            <name>I fill field "div#root div:nth-child(2) > input", "Test@123"</name>
                            <title>I fill field "div#root div:nth-child(2) > input", "Test@123"</title>
                            <attachments/>
                            <steps/>
                        </step>
                        <step start='1703355982005' status='passed' stop='1703355982228'>
                            <name>I click "Sign In"</name>
                            <title>I click "Sign In"</title>
                            <attachments/>
                            <steps/>
                        </step>
                    </steps>
                </step>
                <step start='1703355982228' status='passed' stop='1703355992325'>
                    <name>I wait 10</name>
                    <title>I wait 10</title>
                    <attachments/>
                    <steps/>
                </step>
                <step start='1703355992325' status='passed' stop='1703355992412'>
                    <name>I see "My Workspace"</name>
                    <title>I see "My Workspace"</title>
                    <attachments/>
                    <steps/>
                </step>
                <step start='1703355992412' status='passed' stop='1703355997510'>
                    <name>I wait 5</name>
                    <title>I wait 5</title>
                    <attachments/>
                    <steps/>
                </step>
            </steps>
            <attachments/>
        </test-case>
        <test-case start='1703355997518' status='passed' stop='1703356005085'>
            <name>Project Selection</name>
            <title>Project Selection</title>
            <labels>
                <label name='language' value='javascript'/>
                <label name='framework' value='codeceptjs'/>
            </labels>
            <parameters/>
            <steps>
                <step start='1703355997521' status='passed' stop='1703355997597'>
                    <name>I see "test"</name>
                    <title>I see "test"</title>
                    <attachments/>
                    <steps/>
                </step>
                <step start='1703355997597' status='passed' stop='1703355997887'>
                    <name>I click "test"</name>
                    <title>I click "test"</title>
                    <attachments/>
                    <steps/>
                </step>
                <step start='1703355997887' status='passed' stop='1703356005085'>
                    <name>I wait 7</name>
                    <title>I wait 7</title>
                    <attachments/>
                    <steps/>
                </step>
            </steps>
            <attachments/>
        </test-case>
        <test-case start='1703356005093' status='failed' stop='1703356013502'>
            <name>Draw Rectangle</name>
            <title>Draw Rectangle</title>
            <labels>
                <label name='language' value='javascript'/>
                <label name='framework' value='codeceptjs'/>
            </labels>
            <parameters/>
            <steps>
                <step start='1703356005098' status='passed' stop='1703356007194'>
                    <name>I wait 2</name>
                    <title>I wait 2</title>
                    <attachments/>
                    <steps/>
                </step>
                <step start='1703356007194' status='passed' stop='1703356009296'>
                    <name>I wait 2</name>
                    <title>I wait 2</title>
                    <attachments/>
                    <steps/>
                </step>
                <step start='1703356009297' status='passed' stop='1703356009516'>
                    <name>I press key ["Control","a"]</name>
                    <title>I press key ["Control","a"]</title>
                    <attachments/>
                    <steps/>
                </step>
                <step start='1703356009517' status='passed' stop='1703356009765'>
                    <name>I press key "Delete"</name>
                    <title>I press key "Delete"</title>
                    <attachments/>
                    <steps/>
                </step>
                <step start='1703356009765' status='passed' stop='1703356010866'>
                    <name>I wait 1</name>
                    <title>I wait 1</title>
                    <attachments/>
                    <steps/>
                </step>
                <step start='1703356010866' status='passed' stop='1703356011113'>
                    <name>I click "#canvas"</name>
                    <title>I click "#canvas"</title>
                    <attachments/>
                    <steps/>
                </step>
                <step start='1703356011114' status='passed' stop='1703356012213'>
                    <name>I wait 1</name>
                    <title>I wait 1</title>
                    <attachments/>
                    <steps/>
                </step>
                <step start='1703356012213' status='passed' stop='1703356012437'>
                    <name>I move cursor to "#canvas", 80, </name>
                    <title>I move cursor to "#canvas", 80, </title>
                    <attachments/>
                    <steps/>
                </step>
                <step start='1703356012438' status='failed' stop='1703356013501'>
                    <name>I click </name>
                    <title>I click </title>
                    <attachments/>
                    <steps/>
                </step>
            </steps>
            <attachments>
                <attachment title='Last Seen Screenshot' source='318d7bff-f61f-4546-9278-46ce1b25521a-attachment.png' type='image/png' size='83317'/>
            </attachments>
            <failure>
                <message>Cannot read properties of undefined (reading 'react')</message>
                <stack-trace>TypeError: Cannot read properties of undefined (reading 'react')
                    at Puppeteer.findClickable (D:\snaptrude\node_modules\codeceptjs\lib\helper\Puppeteer.js:2326:15)
                    at Puppeteer.proceedClick (D:\snaptrude\node_modules\codeceptjs\lib\helper\Puppeteer.js:2310:35)</stack-trace>
            </failure>
        </test-case>
    </test-cases>
</ns2:test-suite>